tokenazad/__init__.py
tokenazad/tokenmagic.py
tokenazad/utils/__init__.py
tokenazad/utils/errors.py
tokenazad-0.0.7.dist-info/METADATA
tokenazad-0.0.7.dist-info/WHEEL
tokenazad-0.0.7.dist-info/top_level.txt
tokenazad-0.0.7.dist-info/RECORD
